{
  "id": "4077204",
  "name": "js_011",
  "font_family": "iconfont",
  "css_prefix_text": "icon-",
  "description": "",
  "glyphs": [
    {
      "icon_id": "5387689",
      "name": "地点定位",
      "font_class": "didiandingwei",
      "unicode": "eb31",
      "unicode_decimal": 60209
    },
    {
      "icon_id": "577384",
      "name": "信息",
      "font_class": "xinxi",
      "unicode": "e763",
      "unicode_decimal": 59235
    },
    {
      "icon_id": "2076254",
      "name": "电话",
      "font_class": "dianhua",
      "unicode": "e88b",
      "unicode_decimal": 59531
    },
    {
      "icon_id": "6129261",
      "name": "222扫一扫、扫描",
      "font_class": "saoyisaosaomiao",
      "unicode": "e7c1",
      "unicode_decimal": 59329
    },
    {
      "icon_id": "629357",
      "name": "搜索",
      "font_class": "sousuo",
      "unicode": "e651",
      "unicode_decimal": 58961
    },
    {
      "icon_id": "986196",
      "name": "qq",
      "font_class": "qq-copy",
      "unicode": "e656",
      "unicode_decimal": 58966
    },
    {
      "icon_id": "1221269",
      "name": "微信",
      "font_class": "weixin",
      "unicode": "e60f",
      "unicode_decimal": 58895
    },
    {
      "icon_id": "577339",
      "name": "攻略",
      "font_class": "gonglve",
      "unicode": "e73b",
      "unicode_decimal": 59195
    },
    {
      "icon_id": "4625214",
      "name": "订酒店",
      "font_class": "dingjiudian",
      "unicode": "e6cb",
      "unicode_decimal": 59083
    },
    {
      "icon_id": "32216673",
      "name": "机票",
      "font_class": "changyonglvyouyewutubiao_fuzhi_jipiao",
      "unicode": "e607",
      "unicode_decimal": 58887
    },
    {
      "icon_id": "1249058",
      "name": "旅行",
      "font_class": "lvhang",
      "unicode": "e60e",
      "unicode_decimal": 58894
    },
    {
      "icon_id": "2076297",
      "name": " 机票",
      "font_class": "jipiao",
      "unicode": "e89c",
      "unicode_decimal": 59548
    },
    {
      "icon_id": "2582158",
      "name": "112ETC充值",
      "font_class": "ETCchongzhi",
      "unicode": "e671",
      "unicode_decimal": 58993
    },
    {
      "icon_id": "6195102",
      "name": "打车",
      "font_class": "dache",
      "unicode": "e813",
      "unicode_decimal": 59411
    },
    {
      "icon_id": "6489727",
      "name": "花",
      "font_class": "hua",
      "unicode": "e68c",
      "unicode_decimal": 59020
    },
    {
      "icon_id": "6992718",
      "name": "投诉",
      "font_class": "tousu",
      "unicode": "e67b",
      "unicode_decimal": 59003
    },
    {
      "icon_id": "9748080",
      "name": "酒店",
      "font_class": "jiudian",
      "unicode": "e642",
      "unicode_decimal": 58946
    },
    {
      "icon_id": "11372769",
      "name": "社区",
      "font_class": "shequ",
      "unicode": "e8c5",
      "unicode_decimal": 59589
    },
    {
      "icon_id": "11372774",
      "name": "首页",
      "font_class": "shouye",
      "unicode": "e8c6",
      "unicode_decimal": 59590
    },
    {
      "icon_id": "11771743",
      "name": "文创艺术_icon",
      "font_class": "wenchuangyishu_icon",
      "unicode": "e60a",
      "unicode_decimal": 58890
    },
    {
      "icon_id": "12774741",
      "name": "找找厕所",
      "font_class": "zhaozhaocesuo",
      "unicode": "e63d",
      "unicode_decimal": 58941
    },
    {
      "icon_id": "15341333",
      "name": "门票",
      "font_class": "ziyuan3",
      "unicode": "e602",
      "unicode_decimal": 58882
    },
    {
      "icon_id": "15686496",
      "name": "车辆费2",
      "font_class": "cheliangfei2",
      "unicode": "e6ba",
      "unicode_decimal": 59066
    },
    {
      "icon_id": "15686647",
      "name": "行程",
      "font_class": "hangcheng",
      "unicode": "e6de",
      "unicode_decimal": 59102
    },
    {
      "icon_id": "18371086",
      "name": "我的",
      "font_class": "wode",
      "unicode": "e675",
      "unicode_decimal": 58997
    },
    {
      "icon_id": "26580019",
      "name": "旅行套餐-20",
      "font_class": "lvhangtaocan-20",
      "unicode": "e643",
      "unicode_decimal": 58947
    },
    {
      "icon_id": "29236665",
      "name": "路线明确",
      "font_class": "luxianmingque",
      "unicode": "e600",
      "unicode_decimal": 58880
    },
    {
      "icon_id": "32475736",
      "name": "消息",
      "font_class": "xiaoxi",
      "unicode": "e71b",
      "unicode_decimal": 59163
    },
    {
      "icon_id": "35269641",
      "name": "附近景区",
      "font_class": "fujinjingqu",
      "unicode": "e777",
      "unicode_decimal": 59255
    }
  ]
}
